pydt3/__init__.py
pydt3/application.py
pydt3/helper_bridging.py
pydt3/jxa_helper.scpt
pydt3/objproxy.py
pydt3/osascript.py
pydt3/utils.py
pydt3/apps/devonthink/__init__.py
pydt3/apps/devonthink/database.py
pydt3/apps/devonthink/devonthink.py
pydt3/apps/devonthink/item.py
pydt3/apps/devonthink/record.py
pydt3/apps/devonthink/reminder.py
pydt3/apps/devonthink/smartgroup.py
pydt3/apps/devonthink/tab.py
pydt3/apps/devonthink/text.py
pydt3/apps/devonthink/windows.py
pydt3/apps/mail/__init__.py
pydt3/apps/mail/account.py
pydt3/apps/mail/mail.py
pydt3/apps/mail/mailbox.py
pydt3/apps/mail/message.py
pydt3-0.1.0.dist-info/LICENSE.txt
pydt3-0.1.0.dist-info/METADATA
pydt3-0.1.0.dist-info/WHEEL
pydt3-0.1.0.dist-info/top_level.txt
pydt3-0.1.0.dist-info/utils.py
pydt3-0.1.0.dist-info/RECORD
