Metadata-Version: 2.1
Name: pydt3
Version: 0.1.0
Summary: Python API for Devonthink 3 utilizes AppleScript (JXA) and PyObjC.
Author-email: astrosheep <astrosheepthesheep@outlook.com>
Classifier: Programming Language :: Python :: 3
Classifier: License :: OSI Approved :: MIT License
Classifier: Operating System :: MacOS
Requires-Python: >=3.7
License-File: LICENSE.txt
Requires-Dist: pyobjc-core
Requires-Dist: pyobjc-framework-AppleScriptKit
Requires-Dist: pyobjc-framework-AppleScriptObjC
